sceptre_cdk_handler/__init__.py
sceptre_cdk_handler/cdk.py
sceptre_cdk_handler/cdk_builder.py
sceptre_cdk_handler/class_importer.py
sceptre_cdk_handler/command_checker.py
sceptre_cdk_handler-2.1.0.dist-info/LICENSE
sceptre_cdk_handler-2.1.0.dist-info/METADATA
sceptre_cdk_handler-2.1.0.dist-info/WHEEL
sceptre_cdk_handler-2.1.0.dist-info/entry_points.txt
sceptre_cdk_handler-2.1.0.dist-info/top_level.txt
sceptre_cdk_handler-2.1.0.dist-info/RECORD
