Metadata-Version: 2.1
Name: sceptre-cdk-handler
Version: 2.1.0
Summary: AWS CDK Template Handler
Home-page: https://github.com/sceptre/sceptre-cdk-handler
Author: Sceptre
Author-email: sceptre@sceptre.org
License: Apache2
Keywords: sceptre,sceptre-template-handler
Platform: UNKNOWN
Classifier: Intended Audience :: Developers
Classifier: Natural Language :: English
Classifier: Environment :: Console
Classifier: Programming Language :: Python :: 3.7
Classifier: Programming Language :: Python :: 3.8
Classifier: Programming Language :: Python :: 3.9
Classifier: Programming Language :: Python :: 3.10
License-File: LICENSE
Requires-Dist: sceptre (>=4.0)
Requires-Dist: aws-cdk-lib (<3.0,>=2.0)
Requires-Dist: cdk-bootstrapless-synthesizer (<3.0,>=2.0)
Requires-Dist: typing-extensions
Provides-Extra: test
Requires-Dist: pytest (>=3.2) ; extra == 'test'
